pyclaude/__init__.py
pyclaude/base.py
pyclaude/constraints.py
pyclaude/observables.py
pyclaude/test.py
pyclaude-0.1.1.dist-info/LICENSE.txt
pyclaude-0.1.1.dist-info/METADATA
pyclaude-0.1.1.dist-info/WHEEL
pyclaude-0.1.1.dist-info/top_level.txt
pyclaude-0.1.1.dist-info/RECORD
